ecmind_spring_config/__init__.py
ecmind_spring_config/config.py
ecmind_spring_config-0.1.1.dist-info/LICENSE
ecmind_spring_config-0.1.1.dist-info/METADATA
ecmind_spring_config-0.1.1.dist-info/WHEEL
ecmind_spring_config-0.1.1.dist-info/top_level.txt
ecmind_spring_config-0.1.1.dist-info/RECORD
