Metadata-Version: 2.1
Name: ecmind-spring-config
Version: 0.1.1
Summary: Helper module for spring alike configuration loading plus spring cloud config client
Home-page: https://gitlab.ecmind.ch/open/ecmind_spring_config
Author: Ulrich Wohlfeil
Author-email: info@ecmind.ch
Classifier: Programming Language :: Python :: 3
Classifier: License :: OSI Approved :: MIT License
Classifier: Operating System :: OS Independent
Requires-Python: >=3.8
License-File: LICENSE
Requires-Dist: PyYAML (>=5.4.1)
Requires-Dist: deepmerge (>=0.3.0)
Requires-Dist: toml (>=0.10.2)
